dStorage/LICENSE
dStorage/__init__.py
dStorage/core.py
dstorage-1.1.2rc1.dist-info/WHEEL
dstorage-1.1.2rc1.dist-info/METADATA
dstorage-1.1.2rc1.dist-info/RECORD
