Metadata-Version: 2.1
Name: dStorage
Version: 1.1.2rc1
Summary: dStorage, biblioteca para construção de aplicativos em python.
Home-page: https://github.com/leo0-07/dStorage
Author: Leonardo de Araújo Lima
Author-email: leonardo@asl-sl.com.br
Classifier: License :: OSI Approved :: GNU General Public License v3 or later (GPLv3+)
